Metadata-Version: 1.1
Name: reciprocal-smallest-distance
Version: 1.1.7
Summary: Reciprocal Smallest Distance (RSD) finds pairwise orthologous genes using global sequence alignment and maximum likelihood evolutionary distance estimates.
Home-page: https://github.com/todddeluca/reciprocal_smallest_distance
Author: Todd F. DeLuca, Dennis P. Wall
Author-email: todd_deluca@hms.harvard.edu
License: MIT
Download-URL: https://github.com/todddeluca/reciprocal_smallest_distance/downloads
Keywords: genome ortholog algorithm
Platform: Posix; MacOS X
Classifier: Development Status :: 5 - Production/Stable
Classifier: Environment :: Console
Classifier: Intended Audience :: Science/Research
Classifier: License :: OSI Approved :: MIT License
Classifier: Operating System :: MacOS :: MacOS X
Classifier: Operating System :: POSIX :: Linux
Classifier: Programming Language :: Python
Classifier: Programming Language :: Python :: 2.7
Classifier: Topic :: Scientific/Engineering :: Bio-Informatics
